pytest_prysk/__init__.py
pytest_prysk-0.4.0.dist-info/LICENSE
pytest_prysk-0.4.0.dist-info/METADATA
pytest_prysk-0.4.0.dist-info/WHEEL
pytest_prysk-0.4.0.dist-info/entry_points.txt
pytest_prysk-0.4.0.dist-info/RECORD
