Metadata-Version: 2.1
Name: pytest-prysk
Version: 0.4.0
Summary: Pytest plugin for prysk
Home-page: https://nicoretti.github.io/prysk/
License: GPL-2.0-or-later
Keywords: snapshot testing,functional-tests,testing,pytest,plugin
Author: Nicola Coretti
Author-email: nico.coretti@gmail.com
Requires-Python: >=3.8,<4.0
Classifier: Development Status :: 4 - Beta
Classifier: Environment :: Console
Classifier: Framework :: Pytest
Classifier: Intended Audience :: Developers
Classifier: License :: OSI Approved :: GNU General Public License (GPL)
Classifier: License :: OSI Approved :: GNU General Public License v2 or later (GPLv2+)
Classifier: Natural Language :: English
Classifier: Operating System :: OS Independent
Classifier: Programming Language :: Python :: 3
Classifier: Programming Language :: Python :: 3.8
Classifier: Programming Language :: Python :: 3.9
Classifier: Programming Language :: Python :: 3.10
Classifier: Programming Language :: Python :: 3.11
Classifier: Programming Language :: Unix Shell
Classifier: Topic :: Software Development :: Testing
Requires-Dist: prysk (>=0.15.0)
Requires-Dist: pytest (>=7.3.2)
Project-URL: Repository, https://github.com/prysk/pytest-prysk
